communication/__init__.py
communication/app.py
communication/codegen.py
communication/connect_router.py
communication/decorators.py
communication/entries.py
communication/errors.py
communication/typing_utils.py
vention_communication-0.2.1.dist-info/METADATA
vention_communication-0.2.1.dist-info/WHEEL
vention_communication-0.2.1.dist-info/RECORD
