Metadata-Version: 2.4
Name: vention-communication
Version: 0.2.1
Summary: A framework for communication between machine apps and other services.
License: Proprietary
Author: VentionCo
Requires-Python: >=3.10,<3.11
Classifier: License :: Other/Proprietary License
Classifier: Programming Language :: Python :: 3
Classifier: Programming Language :: Python :: 3.10
Requires-Dist: fastapi (==0.121.1)
Requires-Dist: uvicorn (>=0.35.0,<0.36.0)
